LICENSE
README.md
setup.py
z_zephyr.egg-info/PKG-INFO
z_zephyr.egg-info/SOURCES.txt
z_zephyr.egg-info/dependency_links.txt
z_zephyr.egg-info/requires.txt
z_zephyr.egg-info/top_level.txt
zephyr/__init__.py
zephyr/masking.py
zephyr/nets.py
zephyr/project_typing.py
zephyr/tags.py
zephyr/_nets/__init__.py
zephyr/_nets/attention.py
zephyr/_nets/composition.py
zephyr/_nets/dropout.py
zephyr/_nets/embed.py
zephyr/_nets/linear.py
zephyr/_nets/linear_attention.py
zephyr/_nets/mlp.py
zephyr/_nets/norm.py
zephyr/_nets/pool.py
zephyr/building/__init__.py
zephyr/building/initializers.py
zephyr/building/skeleton.py
zephyr/building/template.py
zephyr/building/tracing.py
zephyr/building/_template/__init__.py
zephyr/building/_template/array.py
zephyr/building/_template/validation.py
zephyr/functools/__init__.py
zephyr/functools/composition.py
zephyr/functools/partial.py