Metadata-Version: 2.1
Name: z-zephyr
Version: 0.0.20
Summary: Zephyr is a declarative neural network library on top of JAX allowing for easy and fast neural network designing, creation, and manipulation
Home-page: https://github.com/mzguntalan/zephyr
Author: Marko Zolo Gozano Untalan
Author-email: mzguntalan@gmail.com
License: Apache-2.0
Classifier: Development Status :: 3 - Alpha
Classifier: Environment :: GPU
Classifier: License :: OSI Approved :: Apache Software License
Classifier: Programming Language :: Python :: 3.11
Classifier: Programming Language :: Python :: 3.12
Classifier: Programming Language :: Python :: 3.13
Classifier: Programming Language :: Python :: 3.14
License-File: LICENSE
Requires-Dist: jax>=0.7.1
Requires-Dist: jaxlib>=0.7.1
